{
    "info": {
        "name": "Laravel JWT API Starter (Auto-Generated)",
        "schema": "https:\/\/schema.getpostman.com\/json\/collection\/v2.1.0\/collection.json"
    },
    "item": [
        {
            "name": "Authentication",
            "item": [
                {
                    "name": "Authenticate user via social provider",
                    "request": {
                        "method": "POST",
                        "header": [
                            {
                                "key": "Accept",
                                "value": "application\/json",
                                "type": "text"
                            }
                        ],
                        "url": {
                            "raw": "{{base_url}}\/auth\/authenticate",
                            "host": [
                                "{{base_url}}"
                            ],
                            "path": [
                                "auth",
                                "authenticate"
                            ]
                        },
                        "description": "### Authenticate user via social provider\n\nAuthenticate a user using social oauth provider and token.\n\n#### Request Body Parameters\n\n| Parameter | Type | Required | Description | Constraints |\n|---|---|---|---|---|\n| `provider` | `string` | Yes |  | Enum: `google`, `facebook`, `apple` |\n| `token` | `string` | Yes |  | - |\n\n### Responses\n\n#### Response: `200`\n\n\n```json\n{\n    \"user\": {\n        \"id\": 42,\n        \"name\": \"veniam et facilis\",\n        \"username\": \"dolorum\",\n        \"email\": \"lbashirian@example.com\",\n        \"email_verified_at\": \"2020-02-22T18:26:30+00:00\",\n        \"avatar\": \"architecto\",\n        \"google_id\": \"non\",\n        \"facebook_id\": \"est\",\n        \"is_onboarding_completed\": \"non\",\n        \"phone_number\": \"(240) 537-8978\",\n        \"phone_iso_code\": \"(619) 805-6289\",\n        \"phone_dial_code\": \"210-521-7323\",\n        \"role\": \"voluptatem\",\n        \"is_active\": true,\n        \"created_at\": \"1978-07-23T07:43:57+00:00\",\n        \"updated_at\": \"1970-08-04T02:31:50+00:00\"\n    },\n    \"authorization\": {\n        \"access_token\": [],\n        \"token_type\": \"enim\",\n        \"expires_in\": \"quas\"\n    }\n}\n```\n\n#### Response: `400`\nOAuth authentication token validation failed.\n\n```json\n{\n    \"error_code\": \"OAUTH_FAILED\",\n    \"exception_type\": \"OauthException\",\n    \"message\": \"OAuth authentication failed. Please check your credentials and try again.\"\n}\n```\n\n#### Response: `403`\nAttempting to login or perform actions with a deactivated account.\n\n```json\n{\n    \"error_code\": \"ACCOUNT_DEACTIVATED\",\n    \"exception_type\": \"AccountDeactivatedException\",\n    \"message\": \"Your account has been deactivated. Please contact support.\"\n}\n```\n\n#### Response: `422`\nValidation error\n\n```json\n{\n    \"error_code\": \"VALIDATION_ERROR\",\n    \"message\": \"The given data was invalid.\",\n    \"errors\": []\n}\n```\n\n",
                        "auth": {
                            "type": "bearer",
                            "bearer": [
                                {
                                    "key": "token",
                                    "value": "{{token}}",
                                    "type": "string"
                                }
                            ]
                        },
                        "body": {
                            "mode": "raw",
                            "raw": "{\n    \"provider\": \"google\",\n    \"token\": \"rerum\"\n}",
                            "options": {
                                "raw": {
                                    "language": "json"
                                }
                            }
                        }
                    },
                    "response": []
                },
                {
                    "name": "Authenticate user",
                    "request": {
                        "method": "POST",
                        "header": [
                            {
                                "key": "Accept",
                                "value": "application\/json",
                                "type": "text"
                            }
                        ],
                        "url": {
                            "raw": "{{base_url}}\/auth\/login",
                            "host": [
                                "{{base_url}}"
                            ],
                            "path": [
                                "auth",
                                "login"
                            ]
                        },
                        "description": "### Authenticate user\n\nAuthenticate a user using their email and password credentials to receive a stateless JWT access token.\n\n#### Request Body Parameters\n\n| Parameter | Type | Required | Description | Constraints |\n|---|---|---|---|---|\n| `email` | `string` | Yes | Authenticating user's email address. | - |\n| `password` | `string` | Yes | Authenticating user's password. | - |\n\n### Responses\n\n#### Response: `200`\n\n\n```json\n{\n    \"user\": {\n        \"id\": 81,\n        \"name\": \"praesentium nisi in\",\n        \"username\": \"qui\",\n        \"email\": \"fkilback@example.com\",\n        \"email_verified_at\": \"2009-03-09T17:44:51+00:00\",\n        \"avatar\": \"dolore\",\n        \"google_id\": \"dolorem\",\n        \"facebook_id\": \"dolorum\",\n        \"is_onboarding_completed\": \"aliquid\",\n        \"phone_number\": \"775-960-1481\",\n        \"phone_iso_code\": \"+1-615-527-6048\",\n        \"phone_dial_code\": \"+1.614.755.1138\",\n        \"role\": \"quia\",\n        \"is_active\": true,\n        \"created_at\": \"1999-10-02T19:40:54+00:00\",\n        \"updated_at\": \"1972-08-16T10:23:15+00:00\"\n    },\n    \"authorization\": {\n        \"access_token\": \"id\",\n        \"token_type\": \"accusamus\",\n        \"expires_in\": 7\n    }\n}\n```\n\n#### Response: `401`\nProviding an incorrect password during login.\n\n```json\n{\n    \"error_code\": \"INVALID_CREDENTIALS\",\n    \"exception_type\": \"InvalidCredentialsException\",\n    \"message\": \"The email or password you entered is incorrect.\"\n}\n```\n\n#### Response: `403`\nAttempting to login or perform actions with a deactivated account.\n\n```json\n{\n    \"error_code\": \"ACCOUNT_DEACTIVATED\",\n    \"exception_type\": \"AccountDeactivatedException\",\n    \"message\": \"Your account has been deactivated. Please contact support.\"\n}\n```\n\n#### Response: `422`\nValidation error\n\n```json\n{\n    \"error_code\": \"VALIDATION_ERROR\",\n    \"message\": \"The given data was invalid.\",\n    \"errors\": []\n}\n```\n\n",
                        "auth": {
                            "type": "bearer",
                            "bearer": [
                                {
                                    "key": "token",
                                    "value": "{{token}}",
                                    "type": "string"
                                }
                            ]
                        },
                        "body": {
                            "mode": "raw",
                            "raw": "{\n    \"email\": \"haylie12@example.org\",\n    \"password\": \"'%KA\\\"O\\\\#T\"\n}",
                            "options": {
                                "raw": {
                                    "language": "json"
                                }
                            }
                        }
                    },
                    "response": []
                },
                {
                    "name": "Logout user",
                    "request": {
                        "method": "POST",
                        "header": [
                            {
                                "key": "Accept",
                                "value": "application\/json",
                                "type": "text"
                            }
                        ],
                        "url": {
                            "raw": "{{base_url}}\/auth\/logout",
                            "host": [
                                "{{base_url}}"
                            ],
                            "path": [
                                "auth",
                                "logout"
                            ]
                        },
                        "description": "### Logout user\n\nRevoke the user's current JWT access token and log them out of the application.\n\n### Responses\n\n#### Response: `204`\nNo content\n\n#### Response: `401`\nRequesting protected routes without a valid JWT token, or token is expired\/invalid.\n\n```json\n{\n    \"error_code\": \"UNAUTHENTICATED\",\n    \"exception_type\": \"AuthenticationException\",\n    \"message\": \"You are not authenticated. Please provide a valid token.\"\n}\n```\n\n",
                        "auth": {
                            "type": "bearer",
                            "bearer": [
                                {
                                    "key": "token",
                                    "value": "{{token}}",
                                    "type": "string"
                                }
                            ]
                        }
                    },
                    "response": []
                },
                {
                    "name": "Refresh token",
                    "request": {
                        "method": "POST",
                        "header": [
                            {
                                "key": "Accept",
                                "value": "application\/json",
                                "type": "text"
                            }
                        ],
                        "url": {
                            "raw": "{{base_url}}\/auth\/refresh",
                            "host": [
                                "{{base_url}}"
                            ],
                            "path": [
                                "auth",
                                "refresh"
                            ]
                        },
                        "description": "### Refresh token\n\nRefresh the user's current authentication token, invalidating the old one and returning a new JWT.\n\n### Responses\n\n#### Response: `200`\n\n\n```json\n{\n    \"user\": {\n        \"id\": 29,\n        \"name\": \"quam omnis veniam\",\n        \"username\": \"quia\",\n        \"email\": \"danielle97@example.net\",\n        \"email_verified_at\": \"1981-09-23T07:40:19+00:00\",\n        \"avatar\": \"veniam\",\n        \"google_id\": \"vel\",\n        \"facebook_id\": \"incidunt\",\n        \"is_onboarding_completed\": \"quibusdam\",\n        \"phone_number\": \"1-360-440-6520\",\n        \"phone_iso_code\": \"+1.817.598.4474\",\n        \"phone_dial_code\": \"412-976-6518\",\n        \"role\": \"sed\",\n        \"is_active\": true,\n        \"created_at\": \"1978-01-22T09:10:50+00:00\",\n        \"updated_at\": \"2010-09-19T02:58:48+00:00\"\n    },\n    \"authorization\": {\n        \"access_token\": \"sapiente\",\n        \"token_type\": \"et\",\n        \"expires_in\": 33\n    }\n}\n```\n\n#### Response: `401`\nRequesting protected routes without a valid JWT token, or token is expired\/invalid.\n\n```json\n{\n    \"error_code\": \"UNAUTHENTICATED\",\n    \"exception_type\": \"AuthenticationException\",\n    \"message\": \"You are not authenticated. Please provide a valid token.\"\n}\n```\n\n",
                        "auth": {
                            "type": "bearer",
                            "bearer": [
                                {
                                    "key": "token",
                                    "value": "{{token}}",
                                    "type": "string"
                                }
                            ]
                        }
                    },
                    "response": []
                },
                {
                    "name": "Register user",
                    "request": {
                        "method": "POST",
                        "header": [
                            {
                                "key": "Accept",
                                "value": "application\/json",
                                "type": "text"
                            }
                        ],
                        "url": {
                            "raw": "{{base_url}}\/auth\/register",
                            "host": [
                                "{{base_url}}"
                            ],
                            "path": [
                                "auth",
                                "register"
                            ]
                        },
                        "description": "### Register user\n\nCreate a new user account with email and password credentials, and return a stateless JWT access token.\n\n#### Request Body Parameters\n\n| Parameter | Type | Required | Description | Constraints |\n|---|---|---|---|---|\n| `name` | `string` | Yes | User's full name. | Max Length: `255` |\n| `email` | `string` | Yes | Unique email address. | Max Length: `255` |\n| `password` | `string` | Yes | Password (must be confirmed). | - |\n| `password_confirmation` | `string` | Yes | Password confirmation (must match password). | - |\n\n### Responses\n\n#### Response: `200`\n\n\n```json\n{\n    \"user\": {\n        \"id\": 14,\n        \"name\": \"corporis laboriosam odit\",\n        \"username\": \"magni\",\n        \"email\": \"jenkins.cathrine@example.net\",\n        \"email_verified_at\": \"1985-02-11T00:22:07+00:00\",\n        \"avatar\": \"beatae\",\n        \"google_id\": \"ipsam\",\n        \"facebook_id\": \"quo\",\n        \"is_onboarding_completed\": \"omnis\",\n        \"phone_number\": \"440.646.8758\",\n        \"phone_iso_code\": \"(254) 247-0102\",\n        \"phone_dial_code\": \"817.988.8319\",\n        \"role\": \"voluptates\",\n        \"is_active\": true,\n        \"created_at\": \"2003-05-22T06:51:10+00:00\",\n        \"updated_at\": \"2014-05-23T05:21:26+00:00\"\n    },\n    \"authorization\": {\n        \"access_token\": \"quia\",\n        \"token_type\": \"iure\",\n        \"expires_in\": 25\n    }\n}\n```\n\n#### Response: `422`\nValidation error\n\n```json\n{\n    \"error_code\": \"VALIDATION_ERROR\",\n    \"message\": \"The given data was invalid.\",\n    \"errors\": []\n}\n```\n\n",
                        "auth": {
                            "type": "bearer",
                            "bearer": [
                                {
                                    "key": "token",
                                    "value": "{{token}}",
                                    "type": "string"
                                }
                            ]
                        },
                        "body": {
                            "mode": "raw",
                            "raw": "{\n    \"name\": \"inventore et asperiores\",\n    \"email\": \"ondricka.marlon@example.com\",\n    \"password\": \"L8x^R0vrv#A$J.\",\n    \"password_confirmation\": \"e}x[>[u`iE\"\n}",
                            "options": {
                                "raw": {
                                    "language": "json"
                                }
                            }
                        }
                    },
                    "response": []
                }
            ]
        },
        {
            "name": "User",
            "item": [
                {
                    "name": "Profile",
                    "item": [
                        {
                            "name": "Update avatar",
                            "request": {
                                "method": "PATCH",
                                "header": [
                                    {
                                        "key": "Accept",
                                        "value": "application\/json",
                                        "type": "text"
                                    }
                                ],
                                "url": {
                                    "raw": "{{base_url}}\/user\/avatar",
                                    "host": [
                                        "{{base_url}}"
                                    ],
                                    "path": [
                                        "user",
                                        "avatar"
                                    ]
                                },
                                "description": "### Update avatar\n\nUpload an avatar file to update the profile.\n\n### Responses\n\n#### Response: `200`\n\n\n```json\n{\n    \"message\": \"et\",\n    \"avatar_url\": \"aut\"\n}\n```\n\n#### Response: `400`\n\n\n```json\n{\n    \"message\": \"quod\"\n}\n```\n\n#### Response: `401`\nRequesting protected routes without a valid JWT token, or token is expired\/invalid.\n\n```json\n{\n    \"error_code\": \"UNAUTHENTICATED\",\n    \"exception_type\": \"AuthenticationException\",\n    \"message\": \"You are not authenticated. Please provide a valid token.\"\n}\n```\n\n#### Response: `422`\nValidation error\n\n```json\n{\n    \"error_code\": \"VALIDATION_ERROR\",\n    \"message\": \"The given data was invalid.\",\n    \"errors\": []\n}\n```\n\n#### Response: `403`\nAttempting to access a route or perform an action without the required user role or permissions.\n\n```json\n{\n    \"error_code\": \"FORBIDDEN\",\n    \"exception_type\": \"AuthorizationException\",\n    \"message\": \"You do not have permission to perform this action.\"\n}\n```\n\n",
                                "auth": {
                                    "type": "bearer",
                                    "bearer": [
                                        {
                                            "key": "token",
                                            "value": "{{token}}",
                                            "type": "string"
                                        }
                                    ]
                                }
                            },
                            "response": []
                        },
                        {
                            "name": "Get profile",
                            "request": {
                                "method": "GET",
                                "header": [
                                    {
                                        "key": "Accept",
                                        "value": "application\/json",
                                        "type": "text"
                                    }
                                ],
                                "url": {
                                    "raw": "{{base_url}}\/user\/me",
                                    "host": [
                                        "{{base_url}}"
                                    ],
                                    "path": [
                                        "user",
                                        "me"
                                    ]
                                },
                                "description": "### Get profile\n\nRetrieve the authenticated user's profile details.\n\n### Responses\n\n#### Response: `200`\n`UserResource`\n\n```json\n{\n    \"user\": {\n        \"id\": 81,\n        \"name\": \"facilis laudantium veniam\",\n        \"username\": \"magni\",\n        \"email\": \"lavon74@example.org\",\n        \"email_verified_at\": \"1995-11-24T13:06:36+00:00\",\n        \"avatar\": \"sed\",\n        \"google_id\": \"architecto\",\n        \"facebook_id\": \"ea\",\n        \"is_onboarding_completed\": \"rerum\",\n        \"phone_number\": \"831-608-5074\",\n        \"phone_iso_code\": \"559.217.4022\",\n        \"phone_dial_code\": \"424-332-9679\",\n        \"role\": \"sint\",\n        \"is_active\": true,\n        \"created_at\": \"1981-10-10T15:40:07+00:00\",\n        \"updated_at\": \"1991-10-23T20:13:02+00:00\"\n    }\n}\n```\n\n#### Response: `401`\nRequesting protected routes without a valid JWT token, or token is expired\/invalid.\n\n```json\n{\n    \"error_code\": \"UNAUTHENTICATED\",\n    \"exception_type\": \"AuthenticationException\",\n    \"message\": \"You are not authenticated. Please provide a valid token.\"\n}\n```\n\n",
                                "auth": {
                                    "type": "bearer",
                                    "bearer": [
                                        {
                                            "key": "token",
                                            "value": "{{token}}",
                                            "type": "string"
                                        }
                                    ]
                                }
                            },
                            "response": []
                        },
                        {
                            "name": "Update password",
                            "request": {
                                "method": "PUT",
                                "header": [
                                    {
                                        "key": "Accept",
                                        "value": "application\/json",
                                        "type": "text"
                                    }
                                ],
                                "url": {
                                    "raw": "{{base_url}}\/user\/password",
                                    "host": [
                                        "{{base_url}}"
                                    ],
                                    "path": [
                                        "user",
                                        "password"
                                    ]
                                },
                                "description": "### Update password\n\nChange the authenticated user's password after validating the current password.\n\n#### Request Body Parameters\n\n| Parameter | Type | Required | Description | Constraints |\n|---|---|---|---|---|\n| `current_password` | `string` | Yes | The user's current password. | - |\n| `password` | `string` | Yes | The new password (must be confirmed and meet security requirements). | - |\n| `password_confirmation` | `string` | Yes | Confirmation of the new password. | - |\n\n### Responses\n\n#### Response: `200`\n`UserResource`\n\n```json\n{\n    \"user\": {\n        \"id\": 22,\n        \"name\": \"tempore in ducimus\",\n        \"username\": \"officiis\",\n        \"email\": \"mccullough.athena@example.com\",\n        \"email_verified_at\": \"1976-09-13T16:45:31+00:00\",\n        \"avatar\": \"id\",\n        \"google_id\": \"voluptas\",\n        \"facebook_id\": \"nihil\",\n        \"is_onboarding_completed\": \"ducimus\",\n        \"phone_number\": \"1-716-367-3624\",\n        \"phone_iso_code\": \"(360) 698-8689\",\n        \"phone_dial_code\": \"515.678.3348\",\n        \"role\": \"velit\",\n        \"is_active\": true,\n        \"created_at\": \"1983-09-30T12:29:07+00:00\",\n        \"updated_at\": \"1987-06-17T17:46:19+00:00\"\n    }\n}\n```\n\n#### Response: `403`\nAttempting to access a route or perform an action without the required user role or permissions.\n\n```json\n{\n    \"error_code\": \"FORBIDDEN\",\n    \"exception_type\": \"AuthorizationException\",\n    \"message\": \"You do not have permission to perform this action.\"\n}\n```\n\n#### Response: `401`\nRequesting protected routes without a valid JWT token, or token is expired\/invalid.\n\n```json\n{\n    \"error_code\": \"UNAUTHENTICATED\",\n    \"exception_type\": \"AuthenticationException\",\n    \"message\": \"You are not authenticated. Please provide a valid token.\"\n}\n```\n\n#### Response: `422`\nValidation error\n\n```json\n{\n    \"error_code\": \"VALIDATION_ERROR\",\n    \"message\": \"The given data was invalid.\",\n    \"errors\": []\n}\n```\n\n",
                                "auth": {
                                    "type": "bearer",
                                    "bearer": [
                                        {
                                            "key": "token",
                                            "value": "{{token}}",
                                            "type": "string"
                                        }
                                    ]
                                },
                                "body": {
                                    "mode": "raw",
                                    "raw": "{\n    \"current_password\": \"u>[sWfL9-T0nyU\",\n    \"password\": \"FZObBwh'%\",\n    \"password_confirmation\": \"{}q]JXxoiE3a\"\n}",
                                    "options": {
                                        "raw": {
                                            "language": "json"
                                        }
                                    }
                                }
                            },
                            "response": []
                        },
                        {
                            "name": "Update profile",
                            "request": {
                                "method": "PUT",
                                "header": [
                                    {
                                        "key": "Accept",
                                        "value": "application\/json",
                                        "type": "text"
                                    }
                                ],
                                "url": {
                                    "raw": "{{base_url}}\/user\/profile",
                                    "host": [
                                        "{{base_url}}"
                                    ],
                                    "path": [
                                        "user",
                                        "profile"
                                    ]
                                },
                                "description": "### Update profile\n\nUpdate the authenticated user's profile information (name and email).\n\n#### Request Body Parameters\n\n| Parameter | Type | Required | Description | Constraints |\n|---|---|---|---|---|\n| `name` | `string` | Yes | Updated full name of the user. | Max Length: `255` |\n| `username` | `string \/ null` | No | Updated username. Must be unique. | Min Length: `3`<br>Max Length: `50` |\n| `phone_number` | `string \/ null` | No | Phone number attributes. | Max Length: `30` |\n| `phone_iso_code` | `string \/ null` | No |  | Max Length: `10` |\n| `phone_dial_code` | `string \/ null` | No |  | Max Length: `10` |\n\n### Responses\n\n#### Response: `200`\n`UserResource`\n\n```json\n{\n    \"user\": {\n        \"id\": 76,\n        \"name\": \"nulla natus porro\",\n        \"username\": \"fugiat\",\n        \"email\": \"calista.brekke@example.com\",\n        \"email_verified_at\": \"2018-01-21T11:43:20+00:00\",\n        \"avatar\": \"similique\",\n        \"google_id\": \"doloribus\",\n        \"facebook_id\": \"consequatur\",\n        \"is_onboarding_completed\": \"ipsa\",\n        \"phone_number\": \"+1 (938) 860-6332\",\n        \"phone_iso_code\": \"+1.707.740.1792\",\n        \"phone_dial_code\": \"+1-812-909-1071\",\n        \"role\": \"adipisci\",\n        \"is_active\": true,\n        \"created_at\": \"1993-04-26T23:19:49+00:00\",\n        \"updated_at\": \"1974-10-09T21:46:58+00:00\"\n    }\n}\n```\n\n#### Response: `403`\nAttempting to access a route or perform an action without the required user role or permissions.\n\n```json\n{\n    \"error_code\": \"FORBIDDEN\",\n    \"exception_type\": \"AuthorizationException\",\n    \"message\": \"You do not have permission to perform this action.\"\n}\n```\n\n#### Response: `401`\nRequesting protected routes without a valid JWT token, or token is expired\/invalid.\n\n```json\n{\n    \"error_code\": \"UNAUTHENTICATED\",\n    \"exception_type\": \"AuthenticationException\",\n    \"message\": \"You are not authenticated. Please provide a valid token.\"\n}\n```\n\n#### Response: `422`\nValidation error\n\n```json\n{\n    \"error_code\": \"VALIDATION_ERROR\",\n    \"message\": \"The given data was invalid.\",\n    \"errors\": []\n}\n```\n\n",
                                "auth": {
                                    "type": "bearer",
                                    "bearer": [
                                        {
                                            "key": "token",
                                            "value": "{{token}}",
                                            "type": "string"
                                        }
                                    ]
                                },
                                "body": {
                                    "mode": "raw",
                                    "raw": "{\n    \"name\": \"aut placeat molestias\",\n    \"username\": \"Ut voluptatem rerum corporis omnis deleniti.\",\n    \"phone_number\": \"480-783-6808\",\n    \"phone_iso_code\": \"(423) 699-6225\",\n    \"phone_dial_code\": \"+1-425-691-0571\"\n}",
                                    "options": {
                                        "raw": {
                                            "language": "json"
                                        }
                                    }
                                }
                            },
                            "response": []
                        },
                        {
                            "name": "Update settings",
                            "request": {
                                "method": "PATCH",
                                "header": [
                                    {
                                        "key": "Accept",
                                        "value": "application\/json",
                                        "type": "text"
                                    }
                                ],
                                "url": {
                                    "raw": "{{base_url}}\/user\/settings",
                                    "host": [
                                        "{{base_url}}"
                                    ],
                                    "path": [
                                        "user",
                                        "settings"
                                    ]
                                },
                                "description": "### Update settings\n\nUpdate user-specific settings such as location sharing, nearby, etc.\n\n#### Request Body Parameters\n\n| Parameter | Type | Required | Description | Constraints |\n|---|---|---|---|---|\n| `location_sharing` | `boolean \/ null` | No |  | - |\n| `nearby` | `boolean \/ null` | No |  | - |\n| `sound_recording` | `boolean \/ null` | No |  | - |\n| `silent_mode` | `boolean \/ null` | No |  | - |\n\n### Responses\n\n#### Response: `200`\n\n\n```json\n{\n    \"message\": \"ut\",\n    \"settings\": [\n        \"sed\"\n    ]\n}\n```\n\n#### Response: `401`\nRequesting protected routes without a valid JWT token, or token is expired\/invalid.\n\n```json\n{\n    \"error_code\": \"UNAUTHENTICATED\",\n    \"exception_type\": \"AuthenticationException\",\n    \"message\": \"You are not authenticated. Please provide a valid token.\"\n}\n```\n\n#### Response: `422`\nValidation error\n\n```json\n{\n    \"error_code\": \"VALIDATION_ERROR\",\n    \"message\": \"The given data was invalid.\",\n    \"errors\": []\n}\n```\n\n#### Response: `403`\nAttempting to access a route or perform an action without the required user role or permissions.\n\n```json\n{\n    \"error_code\": \"FORBIDDEN\",\n    \"exception_type\": \"AuthorizationException\",\n    \"message\": \"You do not have permission to perform this action.\"\n}\n```\n\n",
                                "auth": {
                                    "type": "bearer",
                                    "bearer": [
                                        {
                                            "key": "token",
                                            "value": "{{token}}",
                                            "type": "string"
                                        }
                                    ]
                                },
                                "body": {
                                    "mode": "raw",
                                    "raw": "{\n    \"location_sharing\": true,\n    \"nearby\": true,\n    \"sound_recording\": true,\n    \"silent_mode\": true\n}",
                                    "options": {
                                        "raw": {
                                            "language": "json"
                                        }
                                    }
                                }
                            },
                            "response": []
                        },
                        {
                            "name": "Check username availability",
                            "request": {
                                "method": "GET",
                                "header": [
                                    {
                                        "key": "Accept",
                                        "value": "application\/json",
                                        "type": "text"
                                    }
                                ],
                                "url": {
                                    "raw": "{{base_url}}\/user\/username",
                                    "host": [
                                        "{{base_url}}"
                                    ],
                                    "path": [
                                        "user",
                                        "username"
                                    ],
                                    "query": [
                                        {
                                            "key": "username",
                                            "value": "",
                                            "description": "The username to check for availability.",
                                            "disabled": false
                                        }
                                    ]
                                },
                                "description": "### Check username availability\n\nCheck if a username is valid and available (not taken by another user).\n\n#### Query Parameters\n\n| Parameter | Type | Required | Description | Constraints |\n|---|---|---|---|---|\n| `username` | `string` | Yes | The username to check for availability. | - |\n\n### Responses\n\n#### Response: `200`\n\n\n```json\n{\n    \"available\": true\n}\n```\n\n#### Response: `401`\nRequesting protected routes without a valid JWT token, or token is expired\/invalid.\n\n```json\n{\n    \"error_code\": \"UNAUTHENTICATED\",\n    \"exception_type\": \"AuthenticationException\",\n    \"message\": \"You are not authenticated. Please provide a valid token.\"\n}\n```\n\n#### Response: `422`\nValidation error\n\n```json\n{\n    \"error_code\": \"VALIDATION_ERROR\",\n    \"message\": \"The given data was invalid.\",\n    \"errors\": []\n}\n```\n\n#### Response: `403`\nAttempting to access a route or perform an action without the required user role or permissions.\n\n```json\n{\n    \"error_code\": \"FORBIDDEN\",\n    \"exception_type\": \"AuthorizationException\",\n    \"message\": \"You do not have permission to perform this action.\"\n}\n```\n\n",
                                "auth": {
                                    "type": "bearer",
                                    "bearer": [
                                        {
                                            "key": "token",
                                            "value": "{{token}}",
                                            "type": "string"
                                        }
                                    ]
                                }
                            },
                            "response": []
                        }
                    ]
                }
            ]
        },
        {
            "name": "Admin",
            "item": [
                {
                    "name": "Users",
                    "item": [
                        {
                            "name": "List users",
                            "request": {
                                "method": "GET",
                                "header": [
                                    {
                                        "key": "Accept",
                                        "value": "application\/json",
                                        "type": "text"
                                    }
                                ],
                                "url": {
                                    "raw": "{{base_url}}\/admin\/users",
                                    "host": [
                                        "{{base_url}}"
                                    ],
                                    "path": [
                                        "admin",
                                        "users"
                                    ]
                                },
                                "description": "### List users\n\nList all registered users with pagination.\n\n### Responses\n\n#### Response: `200`\nArray of `UserResource`\n\n```json\n{\n    \"data\": [\n        {\n            \"id\": 78,\n            \"name\": \"similique quod eligendi\",\n            \"username\": \"excepturi\",\n            \"email\": \"noemie66@example.com\",\n            \"email_verified_at\": \"1994-03-22T11:22:10+00:00\",\n            \"avatar\": \"sed\",\n            \"google_id\": \"eius\",\n            \"facebook_id\": \"velit\",\n            \"is_onboarding_completed\": \"et\",\n            \"phone_number\": \"657-576-2659\",\n            \"phone_iso_code\": \"815-687-4493\",\n            \"phone_dial_code\": \"458-266-4303\",\n            \"role\": \"repudiandae\",\n            \"is_active\": true,\n            \"created_at\": \"1973-07-22T00:41:48+00:00\",\n            \"updated_at\": \"2010-02-15T11:41:35+00:00\"\n        }\n    ]\n}\n```\n\n#### Response: `401`\nRequesting protected routes without a valid JWT token, or token is expired\/invalid.\n\n```json\n{\n    \"error_code\": \"UNAUTHENTICATED\",\n    \"exception_type\": \"AuthenticationException\",\n    \"message\": \"You are not authenticated. Please provide a valid token.\"\n}\n```\n\n",
                                "auth": {
                                    "type": "bearer",
                                    "bearer": [
                                        {
                                            "key": "token",
                                            "value": "{{token}}",
                                            "type": "string"
                                        }
                                    ]
                                }
                            },
                            "response": []
                        },
                        {
                            "name": "View user",
                            "request": {
                                "method": "GET",
                                "header": [
                                    {
                                        "key": "Accept",
                                        "value": "application\/json",
                                        "type": "text"
                                    }
                                ],
                                "url": {
                                    "raw": "{{base_url}}\/admin\/users\/:user",
                                    "host": [
                                        "{{base_url}}"
                                    ],
                                    "path": [
                                        "admin",
                                        "users",
                                        ":user"
                                    ],
                                    "variable": [
                                        {
                                            "key": "user",
                                            "value": "1",
                                            "description": "The user ID"
                                        }
                                    ]
                                },
                                "description": "### View user\n\nRetrieve detailed profile information of a specific user.\n\n#### Path Variables\n\n| Parameter | Type | Required | Description | Constraints |\n|---|---|---|---|---|\n| `user` | `integer` | Yes | The user ID | - |\n\n### Responses\n\n#### Response: `200`\n`UserResource`\n\n```json\n{\n    \"user\": {\n        \"id\": 58,\n        \"name\": \"consequatur recusandae quidem\",\n        \"username\": \"ea\",\n        \"email\": \"frohan@example.com\",\n        \"email_verified_at\": \"2018-09-22T15:00:37+00:00\",\n        \"avatar\": \"odio\",\n        \"google_id\": \"earum\",\n        \"facebook_id\": \"illo\",\n        \"is_onboarding_completed\": \"quae\",\n        \"phone_number\": \"463.412.5415\",\n        \"phone_iso_code\": \"+1-704-400-2945\",\n        \"phone_dial_code\": \"(928) 673-7331\",\n        \"role\": \"dignissimos\",\n        \"is_active\": true,\n        \"created_at\": \"2008-07-08T10:20:06+00:00\",\n        \"updated_at\": \"1975-02-25T08:55:36+00:00\"\n    }\n}\n```\n\n#### Response: `404`\nRequesting a database record or resource ID that does not exist.\n\n```json\n{\n    \"error_code\": \"NOT_FOUND\",\n    \"exception_type\": \"ModelNotFoundException\",\n    \"message\": \"The requested resource was not found.\"\n}\n```\n\n#### Response: `401`\nRequesting protected routes without a valid JWT token, or token is expired\/invalid.\n\n```json\n{\n    \"error_code\": \"UNAUTHENTICATED\",\n    \"exception_type\": \"AuthenticationException\",\n    \"message\": \"You are not authenticated. Please provide a valid token.\"\n}\n```\n\n",
                                "auth": {
                                    "type": "bearer",
                                    "bearer": [
                                        {
                                            "key": "token",
                                            "value": "{{token}}",
                                            "type": "string"
                                        }
                                    ]
                                }
                            },
                            "response": []
                        },
                        {
                            "name": "Delete user",
                            "request": {
                                "method": "DELETE",
                                "header": [
                                    {
                                        "key": "Accept",
                                        "value": "application\/json",
                                        "type": "text"
                                    }
                                ],
                                "url": {
                                    "raw": "{{base_url}}\/admin\/users\/:user",
                                    "host": [
                                        "{{base_url}}"
                                    ],
                                    "path": [
                                        "admin",
                                        "users",
                                        ":user"
                                    ],
                                    "variable": [
                                        {
                                            "key": "user",
                                            "value": "1",
                                            "description": "The user ID"
                                        }
                                    ]
                                },
                                "description": "### Delete user\n\nPermanently delete a user account from the system database.\n\n#### Path Variables\n\n| Parameter | Type | Required | Description | Constraints |\n|---|---|---|---|---|\n| `user` | `integer` | Yes | The user ID | - |\n\n### Responses\n\n#### Response: `204`\nNo content\n\n#### Response: `500`\nAn unexpected server error occurred during processing.\n\n```json\n{\n    \"error_code\": \"SERVER_ERROR\",\n    \"exception_type\": \"ServerErrorException\",\n    \"message\": \"Sorry, something went wrong on the server. Please try again later.\"\n}\n```\n\n#### Response: `404`\nRequesting a database record or resource ID that does not exist.\n\n```json\n{\n    \"error_code\": \"NOT_FOUND\",\n    \"exception_type\": \"ModelNotFoundException\",\n    \"message\": \"The requested resource was not found.\"\n}\n```\n\n#### Response: `401`\nRequesting protected routes without a valid JWT token, or token is expired\/invalid.\n\n```json\n{\n    \"error_code\": \"UNAUTHENTICATED\",\n    \"exception_type\": \"AuthenticationException\",\n    \"message\": \"You are not authenticated. Please provide a valid token.\"\n}\n```\n\n",
                                "auth": {
                                    "type": "bearer",
                                    "bearer": [
                                        {
                                            "key": "token",
                                            "value": "{{token}}",
                                            "type": "string"
                                        }
                                    ]
                                }
                            },
                            "response": []
                        },
                        {
                            "name": "Activate user",
                            "request": {
                                "method": "PATCH",
                                "header": [
                                    {
                                        "key": "Accept",
                                        "value": "application\/json",
                                        "type": "text"
                                    }
                                ],
                                "url": {
                                    "raw": "{{base_url}}\/admin\/users\/:user\/activate",
                                    "host": [
                                        "{{base_url}}"
                                    ],
                                    "path": [
                                        "admin",
                                        "users",
                                        ":user",
                                        "activate"
                                    ],
                                    "variable": [
                                        {
                                            "key": "user",
                                            "value": "1",
                                            "description": "The user ID"
                                        }
                                    ]
                                },
                                "description": "### Activate user\n\nReactivate a deactivated user account, allowing them to login and access the platform.\n\n#### Path Variables\n\n| Parameter | Type | Required | Description | Constraints |\n|---|---|---|---|---|\n| `user` | `integer` | Yes | The user ID | - |\n\n### Responses\n\n#### Response: `204`\nNo content\n\n#### Response: `404`\nRequesting a database record or resource ID that does not exist.\n\n```json\n{\n    \"error_code\": \"NOT_FOUND\",\n    \"exception_type\": \"ModelNotFoundException\",\n    \"message\": \"The requested resource was not found.\"\n}\n```\n\n#### Response: `401`\nRequesting protected routes without a valid JWT token, or token is expired\/invalid.\n\n```json\n{\n    \"error_code\": \"UNAUTHENTICATED\",\n    \"exception_type\": \"AuthenticationException\",\n    \"message\": \"You are not authenticated. Please provide a valid token.\"\n}\n```\n\n",
                                "auth": {
                                    "type": "bearer",
                                    "bearer": [
                                        {
                                            "key": "token",
                                            "value": "{{token}}",
                                            "type": "string"
                                        }
                                    ]
                                }
                            },
                            "response": []
                        },
                        {
                            "name": "Deactivate user",
                            "request": {
                                "method": "PATCH",
                                "header": [
                                    {
                                        "key": "Accept",
                                        "value": "application\/json",
                                        "type": "text"
                                    }
                                ],
                                "url": {
                                    "raw": "{{base_url}}\/admin\/users\/:user\/deactivate",
                                    "host": [
                                        "{{base_url}}"
                                    ],
                                    "path": [
                                        "admin",
                                        "users",
                                        ":user",
                                        "deactivate"
                                    ],
                                    "variable": [
                                        {
                                            "key": "user",
                                            "value": "1",
                                            "description": "The user ID"
                                        }
                                    ]
                                },
                                "description": "### Deactivate user\n\nDeactivate a user account, revoking their active token and session immediately.\n\n#### Path Variables\n\n| Parameter | Type | Required | Description | Constraints |\n|---|---|---|---|---|\n| `user` | `integer` | Yes | The user ID | - |\n\n### Responses\n\n#### Response: `204`\nNo content\n\n#### Response: `404`\nRequesting a database record or resource ID that does not exist.\n\n```json\n{\n    \"error_code\": \"NOT_FOUND\",\n    \"exception_type\": \"ModelNotFoundException\",\n    \"message\": \"The requested resource was not found.\"\n}\n```\n\n#### Response: `401`\nRequesting protected routes without a valid JWT token, or token is expired\/invalid.\n\n```json\n{\n    \"error_code\": \"UNAUTHENTICATED\",\n    \"exception_type\": \"AuthenticationException\",\n    \"message\": \"You are not authenticated. Please provide a valid token.\"\n}\n```\n\n",
                                "auth": {
                                    "type": "bearer",
                                    "bearer": [
                                        {
                                            "key": "token",
                                            "value": "{{token}}",
                                            "type": "string"
                                        }
                                    ]
                                }
                            },
                            "response": []
                        },
                        {
                            "name": "Update user role",
                            "request": {
                                "method": "PATCH",
                                "header": [
                                    {
                                        "key": "Accept",
                                        "value": "application\/json",
                                        "type": "text"
                                    }
                                ],
                                "url": {
                                    "raw": "{{base_url}}\/admin\/users\/:user\/role",
                                    "host": [
                                        "{{base_url}}"
                                    ],
                                    "path": [
                                        "admin",
                                        "users",
                                        ":user",
                                        "role"
                                    ],
                                    "variable": [
                                        {
                                            "key": "user",
                                            "value": "1",
                                            "description": "The user ID"
                                        }
                                    ]
                                },
                                "description": "### Update user role\n\nAssign a new system role (user, admin) to a user account.\n\n#### Path Variables\n\n| Parameter | Type | Required | Description | Constraints |\n|---|---|---|---|---|\n| `user` | `integer` | Yes | The user ID | - |\n\n#### Request Body Parameters\n\n| Parameter | Type | Required | Description | Constraints |\n|---|---|---|---|---|\n| `role` | `string` | Yes | The new role to assign to the user. | Enum: `user`, `admin` |\n\n### Responses\n\n#### Response: `204`\nNo content\n\n#### Response: `404`\nRequesting a database record or resource ID that does not exist.\n\n```json\n{\n    \"error_code\": \"NOT_FOUND\",\n    \"exception_type\": \"ModelNotFoundException\",\n    \"message\": \"The requested resource was not found.\"\n}\n```\n\n#### Response: `401`\nRequesting protected routes without a valid JWT token, or token is expired\/invalid.\n\n```json\n{\n    \"error_code\": \"UNAUTHENTICATED\",\n    \"exception_type\": \"AuthenticationException\",\n    \"message\": \"You are not authenticated. Please provide a valid token.\"\n}\n```\n\n#### Response: `422`\nValidation error\n\n```json\n{\n    \"error_code\": \"VALIDATION_ERROR\",\n    \"message\": \"The given data was invalid.\",\n    \"errors\": []\n}\n```\n\n",
                                "auth": {
                                    "type": "bearer",
                                    "bearer": [
                                        {
                                            "key": "token",
                                            "value": "{{token}}",
                                            "type": "string"
                                        }
                                    ]
                                },
                                "body": {
                                    "mode": "raw",
                                    "raw": "{\n    \"role\": \"admin\"\n}",
                                    "options": {
                                        "raw": {
                                            "language": "json"
                                        }
                                    }
                                }
                            },
                            "response": []
                        }
                    ]
                }
            ]
        }
    ],
    "variable": [
        {
            "key": "base_url",
            "value": "http:\/\/localhost\/api",
            "type": "string"
        },
        {
            "key": "token",
            "value": "",
            "type": "string"
        }
    ]
}